sisyphus
