Metadata-Version: 1.0
Name: sisyphus
Version: 0.0.1.4
Summary: Lightweight task processing queue.
Home-page: https://github.com/mkorenkov/sisyphus
Author: mkorenkov
Author-email: mkorenkov@gmail.com
License: Apache License, Version 2.0
Platform: UNKNOWN
